[{"nome":"Morango","preco":"5,00","descricao":"Bandeja 250g","id":"1","Enderecofoto":"uploads\\Produto1.jpg"},{"nome":"Brownie","preco":"6,00","descricao":"","id":"2","Enderecofoto":"uploads\\Produto2.jpg"},{"nome":"Cone de sorvete","preco":"8,00","descricao":"Sabor baunilha","id":3,"Enderecofoto":"uploads\\Produto3.jpg"},{"nome":"Caderno","preco":"15,00","descricao":"Caderno com 96 p\u00e1ginas","id":4,"Enderecofoto":"uploads\\Produto4.jpg"},{"nome":"Cone de sorvete pack","preco":"25,00","descricao":"5 unidades","id":"5","Enderecofoto":"uploads\\Produto5.jpg"}]